func1
func2
