Metadata-Version: 2.1
Name: demo006
Version: 0.0.3
Summary: 发布自己的第三方模块库测试...
Home-page: http://www.52phm.cn
Author: china 52phm
Author-email: 2374521450@qq.com
License: UNKNOWN
Platform: UNKNOWN
